dispute/__init__.py
dispute-0.0.1.dist-info/LICENSE
dispute-0.0.1.dist-info/METADATA
dispute-0.0.1.dist-info/WHEEL
dispute-0.0.1.dist-info/top_level.txt
dispute-0.0.1.dist-info/RECORD
